Workbook

Sheet Cover
B3: INTEGRATED THREE-STATEMENT FINANCIAL MODEL
B4: Ferrari N.V. (NYSE: RACE / MTA: RACE) - Valuation & Forecasting Framework
B10: TARGET COMPANY: | D10: Ferrari N.V.
B11: MODEL HORIZON: | D11: Historical (2023-2025) // Projection (2026-2030)
B12: SCENARIOS INCLUDED: | D12: Base, Case, Upside, Downside (Dynamic Toogle Enabled)
B13: PREPARED BY: | D13: Marco Avellino
B14: DATE OF EMISSION: | D14: 46281
B18: MODEL STRUCTURE & INDEX:
B19: 1. Cover | - Project metadata and layout introductory notes.
B20: 2. Assumptions | - Macroeconomic drivers, scenario toogle engine, and margins.
B21: 3. Income Statement | - Historical revenue performance and operational profitability (EBITDA/EBIT).
B22: 4. Balance Sheet | - Capital structure mapping and automated balancing engine.
B23: 5. Cash Flow Statement | - Cash generation tracking via indirect method and balance check resolution.

Sheet Assumptions 
A1: Seleziona scenario | B1: Base
A3: Voci\Variabili | B3: Unità di misura | C3: 2023 | D3: 2024 | E3: 2025 | F3: 2026 | G3: 2027 | H3: 2028 | I3: 2029 | J3: 2030
A4: Ricavi totali | B4: EUR m | C4: 5970 | D4: 6589 | E4: 7146
A5: di cui auto e ricambi | B5: EUR m | C5: 5122 | D5: 5670 | E5: 6180
A6: di cui sponsor, comm. e brand | B6: EUR m | C6: 572 | D6: 610 | E6: 661
A7: di cui motori e altro | B7: EUR m | C7: 276 | D7: 309 | E7: 305
A8: Costo del venduto | B8: EUR m | C8: -3010 | D8: -3280 | E8: -3515
A9: Spese SG&A | B9: EUR m | C9: -490 | D9: -542 | E9: -585
A10: Spese R&D | B10: EUR m | C10: -913 | D10: -990 | E10: -1046
A11: Ammortamenti | B11: EUR m | C11: 545 | D11: 602 | E11: 662
A12: Oneri finanziari netti | B12: EUR m | C12: -35 | D12: -28 | E12: -42
A13: Aliquota Fiscale effettiva | B13: % | C13: 0.21 | D13: 0.221 | E13: 0.218
A15: Crescita Ricavi totali | D15: 0.104 | E15: 0.085
A16: Costo del venduto\ricavi | C16: 0.504 | D16: 0.498 | E16: 0.492
A17: SG&A\Ricavi | C17: 0.082 | D17: 0.082 | E17: 0.082
A18: R&D\Ricavi | C18: 0.153 | D18: 0.15
A20: Crescita ricavi totali | F20: =IF($B$1="Base", 0.055, IF($B$1="Upside", 0.075, 0.02)) -> 0.055 | G20: =IF($B$1="Base", 0.055, IF($B$1="Upside", 0.075, 0.02)) -> 0.055 | H20: =IF($B$1="Base", 0.055, IF($B$1="Upside", 0.075, 0.02)) -> 0.055 | I20: =IF($B$1="Base", 0.055, IF($B$1="Upside", 0.075, 0.02)) -> 0.055 | J20: =IF($B$1="Base", 0.055, IF($B$1="Upside", 0.075, 0.02)) -> 0.055
A21: Costo del venduto \ ricavi | F21: =IF($B$1="Base", 0.49, IF($B$1="Upside", 0.48, 0.505)) -> 0.49 | G21: =IF($B$1="Base", 0.49, IF($B$1="Upside", 0.48, 0.505)) -> 0.49 | H21: =IF($B$1="Base", 0.49, IF($B$1="Upside", 0.48, 0.505)) -> 0.49 | I21: =IF($B$1="Base", 0.49, IF($B$1="Upside", 0.48, 0.505)) -> 0.49 | J21: =IF($B$1="Base", 0.49, IF($B$1="Upside", 0.48, 0.505)) -> 0.49
A22: SG&A\Ricavi | F22: =IF($B$1="Base", 0.082, IF($B$1="Upside", 0.08, 0.085)) -> 0.082 | G22: =IF($B$1="Base", 0.082, IF($B$1="Upside", 0.08, 0.085)) -> 0.082 | H22: =IF($B$1="Base", 0.082, IF($B$1="Upside", 0.08, 0.085)) -> 0.082 | I22: =IF($B$1="Base", 0.082, IF($B$1="Upside", 0.08, 0.085)) -> 0.082 | J22: =IF($B$1="Base", 0.082, IF($B$1="Upside", 0.08, 0.085)) -> 0.082
A23: R&D\Ricavi | F23: =IF($B$1="Base", 0.145, IF($B$1="Upside", 0.14, 0.15)) -> 0.145 | G23: =IF($B$1="Base", 0.145, IF($B$1="Upside", 0.14, 0.15)) -> 0.145 | H23: =IF($B$1="Base", 0.145, IF($B$1="Upside", 0.14, 0.15)) -> 0.145 | I23: =IF($B$1="Base", 0.145, IF($B$1="Upside", 0.14, 0.15)) -> 0.145 | J23: =IF($B$1="Base", 0.145, IF($B$1="Upside", 0.14, 0.15)) -> 0.145

Sheet Income Statement
A3: Voci di bilancio | B3: Unità | C3: 2023 | D3: 2024 | E3: 2025 | F3: 2026 | G3: 2027 | H3: 2028 | I3: 2029 | J3: 2030
A4: Ricavi totali | B4: EUR m | C4: 5970 | D4: 6589 | E4: 7146 | F4: 7539 | G4: 7954 | H4: 8391 | I4: 8853 | J4: 9340
A5: Costo del venduto | B5: EUR m | C5: -3010 | D5: -3280 | E5: -3515 | F5: -3694 | G5: -3897 | H5: -4112 | I5: -4338 | J5: -4577
A6: EBITDA | B6: EUR m | C6: =C4+C5 -> 2960 | D6: =D4+D5 -> 3309 | E6: =E4+E5 -> 3631 | F6: =F4+F5 -> 3845 | G6: 4057 | H6: 4279 | I6: 4515 | J6: 4763
A7: Spese SG&A | B7: EUR m | C7: -490 | D7: -542 | E7: -585 | F7: -618 | G7: -652 | H7: -688 | I7: -726 | J7: -766
A8: Spese R&D | B8: EUR m | C8: -913 | D8: -990 | E8: -1046 | F8: -1093 | G8: -1153 | H8: -1217 | I8: -1284 | J8: -1354
A9: Ammortamenti | B9: EUR m | C9: -545 | D9: -602 | E9: -662 | F9: -694 | G9: -732 | H9: -772 | I9: -814 | J9: -859
A10: EBIT | B10: EUR m | C10: =C6+C7+C8+C9 -> 1012 | D10: =D6+D7+D8+D9 -> 1175 | E10: =E6+E7+E8+E9 -> 1338 | F10: 1440 | G10: 1520 | H10: 1602 | I10: 1691 | J10: 1784

Sheet Balance Sheet
A3: ASSETS | B3: Unità | C3: 2023 | D3: 2024 | E3: 2025 | F3: 2026 | G3: 2027 | H3: 2028 | I3: 2029 | J3: 2030
A4: Cash & Cash Equivalents | B4: EUR m | C4: 1412 | D4: 1540 | E4: 1710 | F4: ='Cash Flow Statement'!F14 -> 1776 | G4: ='Cash Flow Statement'!G14 -> 1862 | H4: ='Cash Flow Statement'!H14 -> 1969 | I4: ='Cash Flow Statement'!I14 -> 2102 | J4: ='Cash Flow Statement'!J14 -> 2264
A5: Trade receivables | B5: EUR m | C5: 710 | D5: 790 | E5: 851 | F5: 898 | G5: 947 | H5: 1000 | I5: 1055 | J5: 1113
A6: Inventories | B6: EUR m | C6: 620 | D6: 692 | E6: 748 | F6: 786 | G6: 829 | H6: 875 | I6: 923 | J6: 974
A7: PP&E & Intangibles | B7: EUR m | C7: 2840 | D7: 3120 | E7: 3420 | F7: 3625 | G7: 3843 | H7: 4073 | I7: 4318 | J7: 4577
A8: TOT. ASSETS | B8: EUR m | C8: =SUM(C4:C7) -> 5582 | D8: =SUM(D4:D7) -> 6142 | E8: =SUM(E4:E7) -> 6729 | F8: =SUM(F4:F7) -> 7085 | G8: =SUM(G4:G7) -> 7481 | H8: =SUM(H4:H7) -> 7917 | I8: =SUM(I4:I7) -> 8398 | J8: =SUM(J4:J7) -> 8928
A9: LIABILITIES & EQUITY | B9: Unità | C9: 2023 | D9: 2024 | E9: 2025 | F9: 2026 | G9: 2027 | H9: 2028 | I9: 2029 | J9: 2030
A10: Trade Payables | B10: EUR m | C10: 942 | D10: 1012 | E10: 1090 | F10: 1146 | G10: 1209 | H10: 1275 | I10: 1345 | J10: 1419
A11: Total Debt | B11: EUR m | C11: 2650 | D11: 2780 | E11: 2910 | F11: 2910 | G11: 2910 | H11: 2910 | I11: 2910 | J11: 2910
A12: Shareholders' Equity | B12: EUR m | C12: 1990 | D12: 2350 | E12: 2729 | F12: 3029 | G12: 3362 | H12: 3732 | I12: 4143 | J12: 4599
A13: TOT. | B13: EUR m | C13: =SUM(C10:C12) -> 5582 | D13: =SUM(D10:D12) -> 6142 | E13: =SUM(E10:E12) -> 6729 | F13: =SUM(F10:F12) -> 7085 | G13: =SUM(G10:G12) -> 7481 | H13: =SUM(H10:H12) -> 7917 | I13: =SUM(I10:I12) -> 8398 | J13: =SUM(J10:J12) -> 8928
A15: BALANCE CHECK | C15: =C8-C13 -> 0 | D15: =D8-D13 -> 0 | E15: =E8-E13 -> 0 | F15: =F8-F13 -> 0 | G15: =G8-G13 -> 0 | H15: =H8-H13 -> 0 | I15: =I8-I13 -> 0 | J15: =J8-J13 -> 0

Sheet Cash Flow Statement
A3: Voci | B3: Unità | C3: 2023 | D3: 2024 | E3: 2025 | F3: 2026 | G3: 2027 | H3: 2028 | I3: 2029 | J3: 2030
A4: EBIT | B4: EUR m
A5: (+) D&A | B5: EUR m
A6: (-)Variazione del CCN | B6: EUR m
A7: Flusso di cassa operativo | B7: EUR m
A8: (-) Spese in conto capitale | B8: EUR m
A9: Flusso di cassa da investimento | B9: EUR m
A10: (+) Variazione del debito finanziario | B10: EUR m
A11: Flusso di cassa da finanziamento | B11: EUR m
A12: Variazione netta di cassa | B12: EUR m | F12: 66 | G12: 86 | H12: 107 | I12: 133 | J12: 162
A13: Cassa iniziale | B13: EUR m | F13: 1710 | G13: =F14 -> 1776 | H13: =G14 -> 1862 | I13: =H14 -> 1969 | J13: =I14 -> 2102
A14: CASSA FINALE | B14: EUR m | F14: =F12+F13 -> 1776 | G14: =G12+G13 -> 1862 | H14: =H12+H13 -> 1969 | I14: =I12+I13 -> 2102 | J14: =J12+J13 -> 2264
